bytewax_s2/__init__.py
bytewax_s2/_io.py
bytewax_s2/_s2.py
bytewax_s2/_types.py
bytewax_s2/py.typed
bytewax_s2-0.1.2.dist-info/METADATA
bytewax_s2-0.1.2.dist-info/WHEEL
bytewax_s2-0.1.2.dist-info/licenses/LICENSE
bytewax_s2-0.1.2.dist-info/RECORD
