Metadata-Version: 2.4
Name: bytewax-s2
Version: 0.1.2
Summary: Bytewax connector for S2
License-File: LICENSE
Requires-Python: >=3.11
Requires-Dist: bytewax>=0.21.1
Requires-Dist: requests>=2.32.3
Requires-Dist: sseclient-py>=1.8.0
Requires-Dist: types-requests>=2.32.0.20241016
